emailfy/__.main__.py
emailfy/__init__.py
emailfy/deliverability.py
emailfy/exceptions_types.py
emailfy/rfc_constants.py
emailfy/syntax.py
emailfy/validate_email.py
emailfy/version.py
emailfy-0.1.6.dist-info/LICENSE
emailfy-0.1.6.dist-info/METADATA
emailfy-0.1.6.dist-info/WHEEL
emailfy-0.1.6.dist-info/top_level.txt
emailfy-0.1.6.dist-info/RECORD
