Metadata-Version: 2.1
Name: emailfy
Version: 0.1.6
Summary: Emailfy is a powerful Python package designed for comprehensive email address validation. It goes beyond basic syntax checks, providing advanced validation features and deliverability checks to ensure that email addresses are not only correctly formatted but also deliverable in a real-world environment.
Home-page: https://github.com/ChristopherTavaresBR/emailfy
Author: Christopher Yosef
Author-email: aratava82@gmail.com
License: MIT
Requires-Python: >=3.6
License-File: LICENSE
Requires-Dist: dnspython >=2.5.0
Requires-Dist: idna >=2.0.0
Provides-Extra: test
Requires-Dist: pytest ; extra == 'test'
Requires-Dist: pytest-cov ; extra == 'test'
Requires-Dist: mypy ; extra == 'test'
Requires-Dist: pylint ; extra == 'test'
Requires-Dist: black ; extra == 'test'
Requires-Dist: isort ; extra == 'test'
